serialdevicelib/__init__.py
serialdevicelib/functions.py
serialdevicelib/serial_device.py
serialdevicelib-0.1.5.dist-info/licenses/LICENSE
serialdevicelib-0.1.5.dist-info/METADATA
serialdevicelib-0.1.5.dist-info/WHEEL
serialdevicelib-0.1.5.dist-info/top_level.txt
serialdevicelib-0.1.5.dist-info/RECORD
