Metadata-Version: 2.4
Name: serialdevicelib
Version: 0.1.5
Summary: A package for controling serial devices
Author: bobisaperson1
Author-email: Brady Fulham <bfulham@bradyfulham.com>
License-Expression: MIT
Project-URL: Homepage, https://github.com/bfulham/serialdevicelib
Project-URL: Issues, https://github.com/bfulham/serialdevicelib/issues
Classifier: Programming Language :: Python :: 3
Classifier: Operating System :: OS Independent
Requires-Python: >=3.9
License-File: LICENSE
Dynamic: author
Dynamic: license-file
